timetree_exporter/__init__.py
timetree_exporter/__main__.py
timetree_exporter/api/__init__.py
timetree_exporter/api/auth.py
timetree_exporter/api/calendar.py
timetree_exporter/api/const.py
timetree_exporter/event.py
timetree_exporter/formatter.py
timetree_exporter/utils.py
timetree_exporter-0.6.2.dist-info/licenses/LICENSE
timetree_exporter-0.6.2.dist-info/WHEEL
timetree_exporter-0.6.2.dist-info/entry_points.txt
timetree_exporter-0.6.2.dist-info/METADATA
timetree_exporter-0.6.2.dist-info/RECORD
