Metadata-Version: 2.4
Name: timetree-exporter
Version: 0.6.2
Summary: A Tool for Exporting TimeTree Calendar and Convert to iCal format(.ics)
Keywords: timetree,exporter,icalendar,ics
Author: Fong-Chun Tsai
Author-email: Fong-Chun Tsai <eoleedimin@gmail.com>
License-Expression: MIT
License-File: LICENSE
Classifier: Programming Language :: Python :: 3
Classifier: Programming Language :: Python :: 3.9
Classifier: Programming Language :: Python :: 3.10
Classifier: Programming Language :: Python :: 3.11
Classifier: Programming Language :: Python :: 3.12
Classifier: Programming Language :: Python :: 3.13
Classifier: Programming Language :: Python :: 3.14
Classifier: License :: OSI Approved :: MIT License
Classifier: Operating System :: OS Independent
Requires-Dist: icalendar>=6.1.0,<7.0.0
Requires-Dist: tzdata>=2024.2,<2026.0
Requires-Dist: requests>=2.32.5,<3.0.0
Requires-Dist: pwinput-eoleedi>=1.0.3.post1,<2.0.0.0 ; python_full_version < '3.14'
Requires-Python: >=3.9, <4.0
Project-URL: Changelog, https://github.com/eoleedi/TimeTree-exporter/blob/main/CHANGELOG.md
Project-URL: Homepage, https://github.com/eoleedi/TimeTree-Exporter
Project-URL: Issues, https://github.com/eoleedi/TimeTree-Exporter/issues
Project-URL: Repository, https://github.com/eoleedi/TimeTree-Exporter
